[
  {
    "type": "constructor",
    "inputs": [
      {
        "name": "house",
        "type": "address",
        "internalType": "address"
      },
      {
        "name": "controller",
        "type": "address",
        "internalType": "address"
      }
    ],
    "stateMutability": "nonpayable"
  },
  {
    "type": "function",
    "name": "CONTROLLER",
    "inputs": [],
    "outputs": [
      {
        "name": "",
        "type": "address",
        "internalType": "address payable"
      }
    ],
    "stateMutability": "view"
  },
  {
    "type": "function",
    "name": "HOUSE",
    "inputs": [],
    "outputs": [
      {
        "name": "",
        "type": "address",
        "internalType": "address payable"
      }
    ],
    "stateMutability": "view"
  },
  {
    "type": "function",
    "name": "ROUND_DURATION",
    "inputs": [],
    "outputs": [
      {
        "name": "",
        "type": "uint256",
        "internalType": "uint256"
      }
    ],
    "stateMutability": "view"
  },
  {
    "type": "function",
    "name": "allFinished",
    "inputs": [],
    "outputs": [
      {
        "name": "",
        "type": "bool",
        "internalType": "bool"
      }
    ],
    "stateMutability": "view"
  },
  {
    "type": "function",
    "name": "createGame",
    "inputs": [
      {
        "name": "players",
        "type": "address[]",
        "internalType": "address[]"
      },
      {
        "name": "anchor",
        "type": "bytes32",
        "internalType": "bytes32"
      }
    ],
    "outputs": [],
    "stateMutability": "nonpayable"
  },
  {
    "type": "function",
    "name": "currentGame",
    "inputs": [],
    "outputs": [
      {
        "name": "",
        "type": "uint256",
        "internalType": "uint256"
      }
    ],
    "stateMutability": "view"
  },
  {
    "type": "function",
    "name": "deal",
    "inputs": [
      {
        "name": "_newAnchor",
        "type": "bytes32",
        "internalType": "bytes32"
      }
    ],
    "outputs": [],
    "stateMutability": "nonpayable"
  },
  {
    "type": "function",
    "name": "dealActions",
    "inputs": [
      {
        "name": "_newAnchor",
        "type": "bytes32",
        "internalType": "bytes32"
      }
    ],
    "outputs": [],
    "stateMutability": "nonpayable"
  },
  {
    "type": "function",
    "name": "gameId",
    "inputs": [],
    "outputs": [
      {
        "name": "",
        "type": "uint256",
        "internalType": "uint256"
      }
    ],
    "stateMutability": "view"
  },
  {
    "type": "function",
    "name": "games",
    "inputs": [
      {
        "name": "",
        "type": "uint256",
        "internalType": "uint256"
      }
    ],
    "outputs": [
      {
        "name": "phaseStartTime",
        "type": "uint256",
        "internalType": "uint256"
      },
      {
        "name": "playerCount",
        "type": "uint256",
        "internalType": "uint256"
      },
      {
        "name": "roundId",
        "type": "uint256",
        "internalType": "uint256"
      },
      {
        "name": "cardCount",
        "type": "uint256",
        "internalType": "uint256"
      },
      {
        "name": "phase",
        "type": "uint8",
        "internalType": "enum Blackjack.Phase"
      },
      {
        "name": "dealerHand",
        "type": "tuple",
        "internalType": "struct Blackjack.Hand",
        "components": [
          {
            "name": "cards",
            "type": "tuple[]",
            "internalType": "struct Blackjack.Card[]",
            "components": [
              {
                "name": "value",
                "type": "uint8",
                "internalType": "uint8"
              },
              {
                "name": "suit",
                "type": "uint8",
                "internalType": "uint8"
              }
            ]
          },
          {
            "name": "total",
            "type": "uint8",
            "internalType": "uint8"
          },
          {
            "name": "hasUsableAce",
            "type": "bool",
            "internalType": "bool"
          }
        ]
      },
      {
        "name": "anchor",
        "type": "bytes32",
        "internalType": "bytes32"
      }
    ],
    "stateMutability": "view"
  },
  {
    "type": "function",
    "name": "getAllPlayerResolveViews",
    "inputs": [
      {
        "name": "id",
        "type": "uint256",
        "internalType": "uint256"
      }
    ],
    "outputs": [
      {
        "name": "addrs",
        "type": "address[]",
        "internalType": "address[]"
      },
      {
        "name": "bets",
        "type": "uint256[]",
        "internalType": "uint256[]"
      },
      {
        "name": "totals",
        "type": "uint256[]",
        "internalType": "uint256[]"
      },
      {
        "name": "statuses",
        "type": "uint8[]",
        "internalType": "enum Blackjack.PlayerStatus[]"
      }
    ],
    "stateMutability": "view"
  },
  {
    "type": "function",
    "name": "getAnchor",
    "inputs": [],
    "outputs": [
      {
        "name": "",
        "type": "bytes32",
        "internalType": "bytes32"
      }
    ],
    "stateMutability": "view"
  },
  {
    "type": "function",
    "name": "getDealerCardCount",
    "inputs": [
      {
        "name": "id",
        "type": "uint256",
        "internalType": "uint256"
      }
    ],
    "outputs": [
      {
        "name": "",
        "type": "uint256",
        "internalType": "uint256"
      }
    ],
    "stateMutability": "view"
  },
  {
    "type": "function",
    "name": "getDealerTotal",
    "inputs": [
      {
        "name": "id",
        "type": "uint256",
        "internalType": "uint256"
      }
    ],
    "outputs": [
      {
        "name": "",
        "type": "uint256",
        "internalType": "uint256"
      }
    ],
    "stateMutability": "view"
  },
  {
    "type": "function",
    "name": "getDealreHand",
    "inputs": [],
    "outputs": [
      {
        "name": "hand",
        "type": "tuple",
        "internalType": "struct Blackjack.Hand",
        "components": [
          {
            "name": "cards",
            "type": "tuple[]",
            "internalType": "struct Blackjack.Card[]",
            "components": [
              {
                "name": "value",
                "type": "uint8",
                "internalType": "uint8"
              },
              {
                "name": "suit",
                "type": "uint8",
                "internalType": "uint8"
              }
            ]
          },
          {
            "name": "total",
            "type": "uint8",
            "internalType": "uint8"
          },
          {
            "name": "hasUsableAce",
            "type": "bool",
            "internalType": "bool"
          }
        ]
      }
    ],
    "stateMutability": "view"
  },
  {
    "type": "function",
    "name": "getGameInfo",
    "inputs": [
      {
        "name": "id",
        "type": "uint256",
        "internalType": "uint256"
      }
    ],
    "outputs": [
      {
        "name": "phaseStartTime",
        "type": "uint256",
        "internalType": "uint256"
      },
      {
        "name": "playerCount",
        "type": "uint256",
        "internalType": "uint256"
      },
      {
        "name": "roundId",
        "type": "uint256",
        "internalType": "uint256"
      },
      {
        "name": "cardCount",
        "type": "uint256",
        "internalType": "uint256"
      },
      {
        "name": "phase",
        "type": "uint8",
        "internalType": "enum Blackjack.Phase"
      },
      {
        "name": "anchor",
        "type": "bytes32",
        "internalType": "bytes32"
      }
    ],
    "stateMutability": "view"
  },
  {
    "type": "function",
    "name": "getGamePlayerCount",
    "inputs": [
      {
        "name": "id",
        "type": "uint256",
        "internalType": "uint256"
      }
    ],
    "outputs": [
      {
        "name": "",
        "type": "uint256",
        "internalType": "uint256"
      }
    ],
    "stateMutability": "view"
  },
  {
    "type": "function",
    "name": "getPhase",
    "inputs": [],
    "outputs": [
      {
        "name": "",
        "type": "uint8",
        "internalType": "enum Blackjack.Phase"
      }
    ],
    "stateMutability": "view"
  },
  {
    "type": "function",
    "name": "getPlayerCards",
    "inputs": [],
    "outputs": [
      {
        "name": "hand",
        "type": "tuple",
        "internalType": "struct Blackjack.Hand",
        "components": [
          {
            "name": "cards",
            "type": "tuple[]",
            "internalType": "struct Blackjack.Card[]",
            "components": [
              {
                "name": "value",
                "type": "uint8",
                "internalType": "uint8"
              },
              {
                "name": "suit",
                "type": "uint8",
                "internalType": "uint8"
              }
            ]
          },
          {
            "name": "total",
            "type": "uint8",
            "internalType": "uint8"
          },
          {
            "name": "hasUsableAce",
            "type": "bool",
            "internalType": "bool"
          }
        ]
      }
    ],
    "stateMutability": "view"
  },
  {
    "type": "function",
    "name": "getPlayerCount",
    "inputs": [
      {
        "name": "id",
        "type": "uint256",
        "internalType": "uint256"
      }
    ],
    "outputs": [
      {
        "name": "",
        "type": "uint256",
        "internalType": "uint256"
      }
    ],
    "stateMutability": "view"
  },
  {
    "type": "function",
    "name": "getPlayerResolveView",
    "inputs": [
      {
        "name": "id",
        "type": "uint256",
        "internalType": "uint256"
      },
      {
        "name": "index",
        "type": "uint256",
        "internalType": "uint256"
      }
    ],
    "outputs": [
      {
        "name": "addr",
        "type": "address",
        "internalType": "address"
      },
      {
        "name": "bet",
        "type": "uint256",
        "internalType": "uint256"
      },
      {
        "name": "handTotal",
        "type": "uint256",
        "internalType": "uint256"
      },
      {
        "name": "status",
        "type": "uint8",
        "internalType": "enum Blackjack.PlayerStatus"
      }
    ],
    "stateMutability": "view"
  },
  {
    "type": "function",
    "name": "hasPlayed",
    "inputs": [],
    "outputs": [
      {
        "name": "",
        "type": "bool",
        "internalType": "bool"
      }
    ],
    "stateMutability": "view"
  },
  {
    "type": "function",
    "name": "hit",
    "inputs": [],
    "outputs": [],
    "stateMutability": "nonpayable"
  },
  {
    "type": "function",
    "name": "playerRoundOver",
    "inputs": [],
    "outputs": [
      {
        "name": "",
        "type": "bool",
        "internalType": "bool"
      }
    ],
    "stateMutability": "view"
  },
  {
    "type": "function",
    "name": "previewPayout",
    "inputs": [
      {
        "name": "id",
        "type": "uint256",
        "internalType": "uint256"
      },
      {
        "name": "index",
        "type": "uint256",
        "internalType": "uint256"
      }
    ],
    "outputs": [
      {
        "name": "payout",
        "type": "uint256",
        "internalType": "uint256"
      },
      {
        "name": "won",
        "type": "bool",
        "internalType": "bool"
      }
    ],
    "stateMutability": "view"
  },
  {
    "type": "function",
    "name": "stand",
    "inputs": [],
    "outputs": [],
    "stateMutability": "nonpayable"
  },
  {
    "type": "event",
    "name": "CardPlayed",
    "inputs": [
      {
        "name": "seed",
        "type": "bytes32",
        "indexed": false,
        "internalType": "bytes32"
      },
      {
        "name": "card",
        "type": "tuple",
        "indexed": false,
        "internalType": "struct Blackjack.Card",
        "components": [
          {
            "name": "value",
            "type": "uint8",
            "internalType": "uint8"
          },
          {
            "name": "suit",
            "type": "uint8",
            "internalType": "uint8"
          }
        ]
      },
      {
        "name": "player",
        "type": "address",
        "indexed": false,
        "internalType": "address"
      },
      {
        "name": "gameId",
        "type": "uint256",
        "indexed": false,
        "internalType": "uint256"
      }
    ],
    "anonymous": false
  },
  {
    "type": "event",
    "name": "GameCreated",
    "inputs": [
      {
        "name": "gameId",
        "type": "uint256",
        "indexed": false,
        "internalType": "uint256"
      }
    ],
    "anonymous": false
  },
  {
    "type": "event",
    "name": "PlayerAction",
    "inputs": [
      {
        "name": "action",
        "type": "string",
        "indexed": false,
        "internalType": "string"
      }
    ],
    "anonymous": false
  }
]